configurable_lti_consumer/__init__.py
configurable_lti_consumer/configurable_lti_consumer.py
configurable_lti_consumer/exceptions.py
configurable_lti_consumer/load_class.py
configurable_lti_consumer/utils.py
configurable_lti_consumer/static/js/configurable_xblock_lti_consumer.js
configurable_lti_consumer/static/js/vendor/iframeResizer.js
configurable_lti_consumer/static/js/vendor/iframeResizer.min.js
configurable_lti_consumer/templates/html/lti_iframe.html
configurable_lti_consumer/templates/html/lti_launch.html
configurable_lti_consumer/templates/html/student.html
configurable_lti_consumer_xblock-1.4.1.dist-info/LICENSE
configurable_lti_consumer_xblock-1.4.1.dist-info/METADATA
configurable_lti_consumer_xblock-1.4.1.dist-info/WHEEL
configurable_lti_consumer_xblock-1.4.1.dist-info/entry_points.txt
configurable_lti_consumer_xblock-1.4.1.dist-info/top_level.txt
configurable_lti_consumer_xblock-1.4.1.dist-info/RECORD
