Metadata-Version: 2.1
Name: configurable-lti-consumer-xblock
Version: 1.4.1
Summary: This Xblock adds configurability over the original lti_consumer XBlock from edx
Home-page: https://github.com/openfun/xblock-configurable-lti-consumer
Author: Open FUN (France Universite Numerique)
Author-email: fun.dev@fun-mooc.fr
License: AGPL 3.0
Keywords: Django,Open edX,MOOC,XBlock
Platform: UNKNOWN
Classifier: Development Status :: 5 - Production/Stable
Classifier: Framework :: Django
Classifier: Framework :: Django :: 1.8
Classifier: Intended Audience :: Developers
Classifier: License :: OSI Approved :: GNU Affero General Public License v3 or later (AGPLv3+)
Classifier: Natural Language :: English
Classifier: Programming Language :: Python :: 2
Classifier: Programming Language :: Python :: 2.7
Requires-Dist: exrex (==0.10.5)
Provides-Extra: dev
Requires-Dist: twine (==1.11.0) ; extra == 'dev'
